xoscar_ray/__init__.py
xoscar_ray/_version.py
xoscar_ray/conftest.py
xoscar_ray/debug.py
xoscar_ray/backends/__init__.py
xoscar_ray/backends/ray/__init__.py
xoscar_ray/backends/ray/backend.py
xoscar_ray/backends/ray/communication.py
xoscar_ray/backends/ray/driver.py
xoscar_ray/backends/ray/pool.py
xoscar_ray/backends/ray/utils.py
xoscar_ray/metrics/__init__.py
xoscar_ray/metrics/backends/__init__.py
xoscar_ray/metrics/backends/ray/__init__.py
xoscar_ray/metrics/backends/ray/ray_metric.py
xoscar_ray/serialization/__init__.py
xoscar_ray/serialization/ray.py
xoscar_ray-0.0.1.dist-info/LICENSE
xoscar_ray-0.0.1.dist-info/METADATA
xoscar_ray-0.0.1.dist-info/WHEEL
xoscar_ray-0.0.1.dist-info/entry_points.txt
xoscar_ray-0.0.1.dist-info/top_level.txt
xoscar_ray-0.0.1.dist-info/RECORD
