Metadata-Version: 2.1
Name: xoscar-ray
Version: 0.0.1
Summary: Xoscar on Ray.
Home-page: http://github.com/xprobe-inc/xoscar_ray
Author: Qin Xuye
Author-email: qinxuye@xprobe.io
Maintainer: Qin Xuye
Maintainer-email: qinxuye@xprobe.io
License: Apache License 2.0
Platform: UNKNOWN
Classifier: Operating System :: OS Independent
Classifier: Programming Language :: Python
Classifier: Programming Language :: Python :: 3
Classifier: Programming Language :: Python :: 3.8
Classifier: Programming Language :: Python :: 3.9
Classifier: Programming Language :: Python :: 3.10
Classifier: Programming Language :: Python :: 3.11
Classifier: Programming Language :: Python :: Implementation :: CPython
Classifier: Topic :: Software Development :: Libraries
License-File: LICENSE
Requires-Dist: ray (>=1.8.0)
Requires-Dist: xoscar
Provides-Extra: dev
Requires-Dist: black ; extra == 'dev'
Requires-Dist: flake8 (>=3.8.0) ; extra == 'dev'
Requires-Dist: pytest-asyncio (>=0.14.0) ; extra == 'dev'
Requires-Dist: pytest-cov (>=2.5.0) ; extra == 'dev'
Requires-Dist: pytest-forked (>=1.0) ; extra == 'dev'
Requires-Dist: pytest-timeout (>=1.2.0) ; extra == 'dev'
Requires-Dist: pytest (>=3.5.0) ; extra == 'dev'
Requires-Dist: mock (>=4.0.0) ; (python_version < "3.8") and extra == 'dev'
